{
  "Descriptor": {
    "UId": "b0bbea30-ec9f-e827-f9cd-fb86c5ea1e0c",
    "Name": "UsrTrafficLights",
    "ModifiedOnUtc": "\/Date(1763721844000)\/",
    "InstallType": 0,
    "Schema": {
      "UId": "efc8d0c8-df38-412b-bf49-6d4838a10455",
      "Name": "UsrTrafficLights"
    },
    "Columns": [
      {
        "ColumnUId": "6ef2ffe2-f160-d410-c8c2-902f2bd44101",
        "IsForceUpdate": false,
        "IsKey": false,
        "ColumnName": "UsrColumn1",
        "DataTypeValueUId": "325a73b8-0f47-44a0-8412-7606f78003ac"
      },
      {
        "ColumnUId": "9e53fd7c-dde4-4502-a64c-b9e34148108b",
        "IsForceUpdate": false,
        "IsKey": false,
        "ColumnName": "Description",
        "DataTypeValueUId": "ddb3a1ee-07e8-4d62-b7a9-d0e618b00fbd"
      },
      {
        "ColumnUId": "736c30a7-c0ec-4fa9-b034-2552b319b633",
        "IsForceUpdate": false,
        "IsKey": false,
        "ColumnName": "Name",
        "DataTypeValueUId": "ddb3a1ee-07e8-4d62-b7a9-d0e618b00fbd"
      },
      {
        "ColumnUId": "ae0e45ca-c495-4fe7-a39d-3ab7278e1617",
        "IsForceUpdate": false,
        "IsKey": true,
        "ColumnName": "Id",
        "DataTypeValueUId": "23018567-a13c-4320-8687-fd6f9e3699bd"
      }
    ]
  }
}